pyedautils/__init__.py
pyedautils/data_io.py
pyedautils/geopy.py
pyedautils/meteo_swiss.py
pyedautils/plots.py
pyedautils/season.py
pyedautils/data/ele_meter.csv
pyedautils-0.0.11.dist-info/LICENSE.txt
pyedautils-0.0.11.dist-info/METADATA
pyedautils-0.0.11.dist-info/WHEEL
pyedautils-0.0.11.dist-info/top_level.txt
pyedautils-0.0.11.dist-info/RECORD
