Metadata-Version: 2.1
Name: pyedautils
Version: 0.0.11
Summary: Python Energy Data Analysis Utilities
Author: Reto Marek
Project-URL: Homepage, https://github.com/retomarek/pyedautils/
Project-URL: Issues, https://github.com/retomarek/pyedautils/issues
Classifier: Programming Language :: Python :: 3
Classifier: License :: OSI Approved :: MIT License
Classifier: Operating System :: OS Independent
Requires-Python: >=3.9
License-File: LICENSE.txt
